k3sprovision/__init__.py
k3sprovision/cluster.py
k3sprovision/helper.py
k3sprovision/provisioner.py
k3sprovision-0.1.1.dist-info/licenses/LICENSE
k3sprovision-0.1.1.dist-info/METADATA
k3sprovision-0.1.1.dist-info/WHEEL
k3sprovision-0.1.1.dist-info/top_level.txt
k3sprovision-0.1.1.dist-info/RECORD
