Metadata-Version: 2.4
Name: k3sprovision
Version: 0.1.1
Summary: A package for provisioning k3s clusters.
Author-email: Omniopenverse <omniopenverse@gmail.com>
License: MIT License
Requires-Python: >=3.8
License-File: LICENSE
Dynamic: license-file
